appdata/__init__.py
appdata/file_store.py
appdata/kv_store.py
py_appdata-0.0.6.dist-info/WHEEL
py_appdata-0.0.6.dist-info/METADATA
py_appdata-0.0.6.dist-info/RECORD
