Metadata-Version: 2.1
Name: py-appdata
Version: 0.0.6
Summary: Small utility library to provide easy access to files and key-value store in an application directory
Home-page: https://github.com/gedemagt/appdata
License: MIT
Author: Jesper Jensen
Author-email: mail@jeshj.com
Requires-Python: >=3.7
Classifier: License :: OSI Approved :: MIT License
Classifier: Programming Language :: Python :: 3
Classifier: Programming Language :: Python :: 3.10
Classifier: Programming Language :: Python :: 3.7
Classifier: Programming Language :: Python :: 3.8
Classifier: Programming Language :: Python :: 3.9
